pangea_google_genai/__init__.py
pangea_google_genai/client.py
pangea_google_genai/errors.py
pangea_google_genai/models.py
pangea_google_genai/py.typed
pangea_google_genai-0.1.0.dist-info/WHEEL
pangea_google_genai-0.1.0.dist-info/METADATA
pangea_google_genai-0.1.0.dist-info/RECORD
