Metadata-Version: 2.4
Name: pangea-google-genai
Version: 0.1.0
Summary: A wrapper around the Google GenAI Python SDK
Author: Pangea
Author-email: Pangea <support@pangea.cloud>
License-Expression: Apache-2.0
Requires-Dist: google-genai>=1.32.0
Requires-Dist: pangea-sdk>=6.6.0
Requires-Dist: typing-extensions>=4.15.0
Requires-Python: >=3.10
